{
  "name": "apidoc-example",
  "version": "0.3.0",
  "description": "apiDoc example project",
  "title": "Custom apiDoc browser title",
  "url": "https://api.github.com/v1",
  "header": {
    "title": "My own header title",
    "content": ""
  },
  "footer": {
    "title": "My own footer title",
    "content": ""
  },
  "order": [
    "GetUser",
    "PostUser"
  ],
  "template": {
    "withCompare": true,
    "withGenerator": true
  },
  "sampleUrl": false,
  "defaultVersion": "0.0.0",
  "apidoc": "0.3.0",
  "generator": {
    "name": "apidoc",
    "time": "2017-12-26T10:22:58.708Z",
    "url": "http://apidocjs.com",
    "version": "0.17.6"
  }
}
